markmap_export/__init__.py
markmap_export/cli.py
markmap_export/core.py
markmap_export-0.2.1.dist-info/METADATA
markmap_export-0.2.1.dist-info/WHEEL
markmap_export-0.2.1.dist-info/entry_points.txt
markmap_export-0.2.1.dist-info/RECORD
