Metadata-Version: 2.4
Name: markmap-export
Version: 0.2.1
Summary: Export Markmap mind maps to high-resolution PNG images
Project-URL: Homepage, https://github.com/metrovoc/markmap-export
Project-URL: Repository, https://github.com/metrovoc/markmap-export
Author-email: metrovoc <metrovoc@gmail.com>
License: MIT
Keywords: export,markmap,mindmap,png,screenshot
Classifier: Development Status :: 4 - Beta
Classifier: Environment :: Console
Classifier: Intended Audience :: Developers
Classifier: License :: OSI Approved :: MIT License
Classifier: Programming Language :: Python :: 3
Classifier: Programming Language :: Python :: 3.9
Classifier: Programming Language :: Python :: 3.10
Classifier: Programming Language :: Python :: 3.11
Classifier: Programming Language :: Python :: 3.12
Classifier: Topic :: Multimedia :: Graphics :: Capture :: Screen Capture
Requires-Python: >=3.9
Requires-Dist: playwright>=1.40.0
Requires-Dist: rich>=13.0.0
Requires-Dist: typer>=0.9.0
